Metadata-Version: 2.1
Name: passax
Version: 1.20
Summary: Retrieve saved passwords. Currenly working for Chrome-based Linux & Windows browsers.
Home-page: https://github.com/auax/passax
Author: Auax
Author-email: auax.dev@gmail.com
License: MIT
Keywords: password,login,data,chrome,brave,opera,windows,linux,browser,info
Platform: UNKNOWN
Classifier: License :: OSI Approved :: MIT License
Classifier: Programming Language :: Python :: 3
Classifier: Development Status :: 4 - Beta
Classifier: Intended Audience :: Developers
Classifier: Topic :: Security
Classifier: Programming Language :: Python :: 3.9
License-File: LICENSE
